NanoSSO/__init__.py
NanoSSO/__main__.py
NanoSSO/__version__.py
NanoSSO-0.1.dist-info/LICENSE
NanoSSO-0.1.dist-info/METADATA
NanoSSO-0.1.dist-info/WHEEL
NanoSSO-0.1.dist-info/entry_points.txt
NanoSSO-0.1.dist-info/top_level.txt
NanoSSO-0.1.dist-info/RECORD
