Metadata-Version: 2.1
Name: NanoSSO
Version: 0.1
Summary: Simple SSO library for handling OAuth2 with the EVE Online ESI API
Home-page: https://github.com/NullsecSpace/NanoSSO
Author-email: maintainers@nullsec.space
License: MIT License
Project-URL: Documentation, https://NanoSSO.nullsec.space
Project-URL: Source, https://github.com/NullsecSpace/NanoSSO
Project-URL: Tracker, https://github.com/NullsecSpace/NanoSSO/issues
Keywords: eve online sso esi oauth2
Classifier: Development Status :: 2 - Pre-Alpha
Classifier: Programming Language :: Python :: 3.10
Classifier: Topic :: Games/Entertainment
Classifier: License :: OSI Approved :: MIT License
Requires-Python: >=3.7
License-File: LICENSE
Requires-Dist: pytest (~=7.2.0)
